queuedir/__init__.py
queuedir/__main__.py
queuedir/cli.py
queuedir/config.py
queuedir/executor.py
queuedir/filestate.py
queuedir/watcher.py
queuedir-1.1.0.dist-info/licenses/LICENSE
queuedir-1.1.0.dist-info/METADATA
queuedir-1.1.0.dist-info/WHEEL
queuedir-1.1.0.dist-info/entry_points.txt
queuedir-1.1.0.dist-info/top_level.txt
queuedir-1.1.0.dist-info/RECORD
