Metadata-Version: 2.4
Name: queuedir
Version: 1.1.0
Summary: A lightweight folder-based job queue system
License: MIT
Requires-Python: >=3.9
License-File: LICENSE
Requires-Dist: watchdog>=3.0.0
Dynamic: license-file
